turberfield_catchphrase-0.25.0-py3.9-nspkg.pth
turberfield/catchphrase/__init__.py
turberfield/catchphrase/matcher.py
turberfield/catchphrase/mediator.py
turberfield/catchphrase/parser.py
turberfield/catchphrase/presenter.py
turberfield/catchphrase/render.py
turberfield/catchphrase/css/__init__.py
turberfield/catchphrase/css/catchphrase.css
turberfield/catchphrase/test/__init__.py
turberfield/catchphrase/test/test_matcher.py
turberfield/catchphrase/test/test_mediator.py
turberfield/catchphrase/test/test_parser.py
turberfield/catchphrase/test/test_presenter.py
turberfield/catchphrase/test/test_render.py
turberfield/catchphrase/test/test_state.py
turberfield/catchphrase/test/test_types.py
turberfield_catchphrase-0.25.0.dist-info/LICENSE
turberfield_catchphrase-0.25.0.dist-info/METADATA
turberfield_catchphrase-0.25.0.dist-info/WHEEL
turberfield_catchphrase-0.25.0.dist-info/namespace_packages.txt
turberfield_catchphrase-0.25.0.dist-info/top_level.txt
turberfield_catchphrase-0.25.0.dist-info/RECORD
