Metadata-Version: 2.1
Name: turberfield-catchphrase
Version: 0.25.0
Summary: A Python framework for parser-based web adventures.
Home-page: https://github.com/tundish/turberfield-catchphrase/issues
Author: D Haynes
Author-email: tundish@gigeconomy.org.uk
License: UNKNOWN
Platform: UNKNOWN
Classifier: Operating System :: POSIX
Classifier: Programming Language :: Python :: 3.9
Classifier: License :: OSI Approved :: GNU General Public License v3 or later (GPLv3+)
License-File: LICENSE
Requires-Dist: turberfield-dialogue (>=0.39.0)
Requires-Dist: turberfield-utils (>=0.38.0)
